go_defer.py
go_defer-1.0.1.dist-info/DESCRIPTION.rst
go_defer-1.0.1.dist-info/METADATA
go_defer-1.0.1.dist-info/RECORD
go_defer-1.0.1.dist-info/WHEEL
go_defer-1.0.1.dist-info/metadata.json
go_defer-1.0.1.dist-info/top_level.txt
